skapex/__init__.py
skapex/inner_ap.cpp
skapex/inner_ap.pyx
skapex/inner_ap.cpython-38-x86_64-linux-gnu.so
skapex/leveraged_affinity_propagation.py
skapex-0.2.1.dist-info/WHEEL
skapex-0.2.1.dist-info/LICENSE.md
skapex-0.2.1.dist-info/METADATA
skapex-0.2.1.dist-info/RECORD
skapex-0.2.1.dist-info/top_level.txt
