Metadata-Version: 2.1
Name: skapex
Version: 0.2.1
Summary: Leveraged Affinity Propagation implementation
Author-email: UO269787 <UO269787@uniovi.es>
Classifier: License :: OSI Approved :: BSD License
Classifier: Programming Language :: Python
Classifier: Programming Language :: Python :: Implementation :: CPython
Requires-Python: >=3.7
License-File: LICENSE.md
